benp_thou_pound/__init__.py
benp_thou_pound/proctor_goals.py
benp_thou_pound-0.0.2.dist-info/LICENSE
benp_thou_pound-0.0.2.dist-info/METADATA
benp_thou_pound-0.0.2.dist-info/WHEEL
benp_thou_pound-0.0.2.dist-info/top_level.txt
benp_thou_pound-0.0.2.dist-info/RECORD
